setup.py
docs/conf.py
examples/client_example/client_example.py
examples/repo_example/basic_repo.py
examples/repo_example/hashed_bin_delegation.py
examples/repo_example/succinct_hash_bin_delegations.py
tuf/__init__.py
tuf/developer_tool.py
tuf/download.py
tuf/exceptions.py
tuf/formats.py
tuf/keydb.py
tuf/log.py
tuf/mirrors.py
tuf/repository_lib.py
tuf/repository_tool.py
tuf/roledb.py
tuf/settings.py
tuf/sig.py
tuf/unittest_toolbox.py
tuf/api/__init__.py
tuf/api/exceptions.py
tuf/api/metadata.py
tuf/api/serialization/__init__.py
tuf/api/serialization/json.py
tuf/ngclient/__init__.py
tuf/ngclient/config.py
tuf/ngclient/fetcher.py
tuf/ngclient/updater.py
tuf/ngclient/_internal/__init__.py
tuf/ngclient/_internal/requests_fetcher.py
tuf/ngclient/_internal/trusted_metadata_set.py
tuf/scripts/__init__.py
tuf/scripts/client.py
tuf/scripts/repo.py
oll_tuf-0.20.0.dev3.dist-info/METADATA
oll_tuf-0.20.0.dev3.dist-info/WHEEL
oll_tuf-0.20.0.dev3.dist-info/entry_points.txt
oll_tuf-0.20.0.dev3.dist-info/license_files/LICENSE
oll_tuf-0.20.0.dev3.dist-info/license_files/LICENSE-MIT
oll_tuf-0.20.0.dev3.dist-info/RECORD
